LICENSE
README.md
setup.py
notifierr/__init__.py
notifierr/__main__.py
notifierr/cli.py
notifierr/config.py
notifierr/core.py
notifierr/strings.py
notifierr/version.py
notifierr.egg-info/PKG-INFO
notifierr.egg-info/SOURCES.txt
notifierr.egg-info/dependency_links.txt
notifierr.egg-info/entry_points.txt
notifierr.egg-info/requires.txt
notifierr.egg-info/top_level.txt
notifierr/sms/__init__.py
notifierr/sms/handler.py
notifierr/sms/providers/__init__.py
notifierr/sms/providers/twilio.py