Metadata-Version: 2.1
Name: notifierr
Version: 0.1.12
Summary: An API server to receive webhook events from Sonarr and Radarr and send SMS messages.
Home-page: https://github.com/adamsbytes/notifierr
Author: adamsbytes
Author-email: adamsbytescode@gmail.com
License: GPLv3
Platform: UNKNOWN
Classifier: Development Status :: 4 - Beta
Classifier: Framework :: Flask
Classifier: License :: OSI Approved :: GNU Lesser General Public License v3 (LGPLv3)
Classifier: Operating System :: OS Independent
Classifier: Programming Language :: Python :: 3
Classifier: Programming Language :: Python :: 3.6
Classifier: Programming Language :: Python :: 3.7
Classifier: Programming Language :: Python :: 3.8
Classifier: Programming Language :: Python :: 3.9
Classifier: Programming Language :: Python :: 3.10
Classifier: Topic :: Home Automation
Requires-Python: >=3.6.0
License-File: LICENSE
